setup.py
gsdata/__init__.py
gsdata/gsdata.py
gsdata/signature.py
gsdata.egg-info/PKG-INFO
gsdata.egg-info/SOURCES.txt
gsdata.egg-info/dependency_links.txt
gsdata.egg-info/requires.txt
gsdata.egg-info/top_level.txt