Metadata-Version: 1.0
Name: gsdata
Version: 1.1.0
Summary: gsdata unoffical python sdk
Home-page: https://github.com/superalsrk/gsdata-python-sdk
Author: SRK.Lyu
Author-email: superalsrk@gmail.com
License: MIT
Keywords: gsdata unoffical python sdk
Platform: UNKNOWN
Classifier: License :: OSI Approved :: MIT License
Classifier: Programming Language :: Python
Classifier: Development Status :: 4 - Beta
Classifier: Intended Audience :: Developers
Classifier: Topic :: Internet :: WWW/HTTP
Classifier: Programming Language :: Python
Classifier: Programming Language :: Python :: 2.7
Classifier: Programming Language :: Python :: 3
Classifier: Programming Language :: Python :: 3.2
Classifier: Programming Language :: Python :: 3.3
Classifier: Programming Language :: Python :: 3.4
Classifier: Programming Language :: Python :: 3.5
